conduktor_public_api_client/__init__.py
conduktor_public_api_client/api/__init__.py
conduktor_public_api_client/api/certificates/__init__.py
conduktor_public_api_client/api/certificates/add_a_certificate.py
conduktor_public_api_client/api/certificates/delete_a_certificate.py
conduktor_public_api_client/api/certificates/delete_certificates.py
conduktor_public_api_client/api/certificates/list_certificates.py
conduktor_public_api_client/api/certificates/tls_check.py
conduktor_public_api_client/api/certificates/upload_a_certificate.py
conduktor_public_api_client/api/cluster/__init__.py
conduktor_public_api_client/api/cluster/create_or_update_a_cluster.py
conduktor_public_api_client/api/cluster/delete_a_cluster.py
conduktor_public_api_client/api/cluster/get_a_cluster.py
conduktor_public_api_client/api/cluster/list_all_clusters.py
conduktor_public_api_client/api/groups/__init__.py
conduktor_public_api_client/api/groups/add_permissions.py
conduktor_public_api_client/api/groups/create_a_group.py
conduktor_public_api_client/api/groups/create_or_update_a_group.py
conduktor_public_api_client/api/groups/delete_a_group.py
conduktor_public_api_client/api/groups/delete_all_permissions.py
conduktor_public_api_client/api/groups/delete_permissions.py
conduktor_public_api_client/api/groups/get_a_group.py
conduktor_public_api_client/api/groups/get_permissions.py
conduktor_public_api_client/api/groups/list_all_groups.py
conduktor_public_api_client/api/groups/set_permissions.py
conduktor_public_api_client/api/users/__init__.py
conduktor_public_api_client/api/users/add_permissions.py
conduktor_public_api_client/api/users/delete_a_user.py
conduktor_public_api_client/api/users/delete_all_permissions.py
conduktor_public_api_client/api/users/delete_permissions.py
conduktor_public_api_client/api/users/get_permissions.py
conduktor_public_api_client/api/users/get_the_list_of_users.py
conduktor_public_api_client/api/users/get_user.py
conduktor_public_api_client/api/users/set_permissions.py
conduktor_public_api_client-0.0.1.dist-info/LICENSE
conduktor_public_api_client-0.0.1.dist-info/METADATA
conduktor_public_api_client-0.0.1.dist-info/WHEEL
conduktor_public_api_client-0.0.1.dist-info/RECORD
