Metadata-Version: 2.1
Name: conduktor-public-api-client
Version: 0.0.1
Summary: A client library for accessing Conduktor Public API
License: LICENSE
Keywords: conduktor,kafka
Author: John "Preston" Mille
Author-email: john@ews-network.net
Requires-Python: >=3.8,<4.0
Classifier: Development Status :: 2 - Pre-Alpha
Classifier: Intended Audience :: Developers
Classifier: Intended Audience :: System Administrators
Classifier: License :: OSI Approved :: Apache Software License
Classifier: License :: Other/Proprietary License
Classifier: Natural Language :: English
Classifier: Programming Language :: Python :: 3
Classifier: Programming Language :: Python :: 3.8
Classifier: Programming Language :: Python :: 3.9
Classifier: Programming Language :: Python :: 3.10
Classifier: Programming Language :: Python :: 3.11
Requires-Dist: attrs (>=21.3.0)
Requires-Dist: httpx (>=0.20.0,<0.25.0)
Requires-Dist: python-dateutil (>=2.8.0,<3.0.0)
